{
    "geometrical_parameters": {
        "fiber_diameter": 0.019622073578595318,
        "blade_distance": 0.19866220735785955,
        "elliptical_fiber_ratio": 1.2959866220735785,
        "ratio_droplet_embedded_length": 1.36,
        "droplet_diameter": 0.162,
        "contact_angle": 25.7,
        "fiber_rotation": 0
    },
    "mechanical_parameters": {
        "interface_friction": 0.0,
        "GI": 0.0015,
        "GII,GIII": 0.07063545150501672,
        "blade_friction": 0.0,
        "tI=tII=tIII": 1.483277591973244
    }
}
