{
    "geometrical_parameters": {
        "fiber_diameter": 0.021,
        "blade_distance": 0.042,
        "elliptical_fiber_ratio": 1.0,
        "ratio_droplet_embedded_length": 1.36,
        "droplet_diameter": 0.162,
        "contact_angle": 25.7,
        "fiber_rotation": 0
    },
    "mechanical_parameters": {
        "interface_friction": 0.24242424242424243,
        "GI": 0.07800000000000001,
        "GII,GIII": 0.55,
        "tI=tII=tIII": 1.4242424242424243,
        "blade_friction": 0.04040404040404041
    }
}
