{
    "geometrical_parameters": {
        "fiber_diameter": 0.021,
        "blade_distance": 0.15,
        "elliptical_fiber_ratio": 1.0,
        "ratio_droplet_embedded_length": 1.36,
        "droplet_diameter": 0.162,
        "contact_angle": 25.7,
        "fiber_rotation": 0
    },
    "mechanical_parameters": {
        "interface_friction": 0.037458193979933115,
        "tI": 0.7227424749163879,
        "tII,tIII": 1.1973244147157192,
        "GI": 0.041725752508361205,
        "GII,GIII": 0.011638795986622074,
        "blade_friction": 0.16321070234113713
    }
}
