{
    "geometrical_parameters": {
        "fiber_diameter": 0.021,
        "blade_distance": 0.15,
        "elliptical_fiber_ratio": 1.0,
        "ratio_droplet_embedded_length": 1.36,
        "droplet_diameter": 0.162,
        "contact_angle": 25.7,
        "fiber_rotation": 0
    },
    "mechanical_parameters": {
        "interface_friction": 0.30769230769230765,
        "GI": 0.007622073578595319,
        "GII,GIII": 0.10177257525083612,
        "tI=tII=tIII": 0.5351170568561873,
        "blade_friction": 0.2193979933110368
    }
}
