{
    "geometrical_parameters": {
        "fiber_diameter": 0.021,
        "blade_distance": 0.15,
        "elliptical_fiber_ratio": 1.0,
        "ratio_droplet_embedded_length": 1.36,
        "droplet_diameter": 0.162,
        "contact_angle": 25.7,
        "fiber_rotation": 0
    },
    "mechanical_parameters": {
        "interface_friction": 0.0026755852842809368,
        "tI": 0.49331103678929766,
        "tII,tIII": 1.939799331103679,
        "GI": 0.044374581939799325,
        "GII,GIII": 0.2214046822742475,
        "blade_friction": 0.22474916387959862
    }
}
