{
    "geometrical_parameters": {
        "fiber_diameter": 0.02714715719063545,
        "blade_distance": 0.4929765886287625,
        "elliptical_fiber_ratio": 1.2909698996655519,
        "ratio_droplet_embedded_length": 1.3269565217391304,
        "droplet_diameter": 0.10657859531772576,
        "contact_angle": 22.113043478260867,
        "fiber_rotation": 69.83277591973243
    },
    "mechanical_parameters": {
        "interface_friction": 0.0,
        "GI": 0.0015,
        "GII,GIII": 0.3,
        "tI=tII=tIII": 1.3,
        "blade_friction": 0.6
    }
}
